tinymce/__init__.py
tinymce/admin.py
tinymce/apps.py
tinymce/config.py
tinymce/fields.py
tinymce/forms.py
tinymce/models.py
tinymce/tests.py
tinymce/urls.py
tinymce/views.py
tinymce/widgets.py
tinymce/migrations/__init__.py
tinymce/static/tinymce/license.txt
tinymce/static/tinymce/tinymce.d.ts
tinymce/static/tinymce/tinymce.min.js
tinymce/static/tinymce/icons/default/icons.min.js
tinymce/static/tinymce/langs/README.md
tinymce/static/tinymce/langs/zh-Hans.js
tinymce/static/tinymce/models/dom/model.min.js
tinymce/static/tinymce/plugins/accordion/plugin.min.js
tinymce/static/tinymce/plugins/advlist/plugin.min.js
tinymce/static/tinymce/plugins/anchor/plugin.min.js
tinymce/static/tinymce/plugins/autolink/plugin.min.js
tinymce/static/tinymce/plugins/autoresize/plugin.min.js
tinymce/static/tinymce/plugins/autosave/plugin.min.js
tinymce/static/tinymce/plugins/charmap/plugin.min.js
tinymce/static/tinymce/plugins/code/plugin.min.js
tinymce/static/tinymce/plugins/codesample/plugin.min.js
tinymce/static/tinymce/plugins/directionality/plugin.min.js
tinymce/static/tinymce/plugins/emoticons/plugin.min.js
tinymce/static/tinymce/plugins/emoticons/js/emojiimages.js
tinymce/static/tinymce/plugins/emoticons/js/emojiimages.min.js
tinymce/static/tinymce/plugins/emoticons/js/emojis.js
tinymce/static/tinymce/plugins/emoticons/js/emojis.min.js
tinymce/static/tinymce/plugins/fullscreen/plugin.min.js
tinymce/static/tinymce/plugins/help/plugin.min.js
tinymce/static/tinymce/plugins/help/js/i18n/keynav/ar.js
tinymce/static/tinymce/plugins/help/js/i18n/keynav/bg_BG.js
tinymce/static/tinymce/plugins/help/js/i18n/keynav/ca.js
tinymce/static/tinymce/plugins/help/js/i18n/keynav/cs.js
tinymce/static/tinymce/plugins/help/js/i18n/keynav/da.js
tinymce/static/tinymce/plugins/help/js/i18n/keynav/de.js
tinymce/static/tinymce/plugins/help/js/i18n/keynav/el.js
tinymce/static/tinymce/plugins/help/js/i18n/keynav/en.js
tinymce/static/tinymce/plugins/help/js/i18n/keynav/es.js
bayketinymce_django-0.0.1.dist-info/LICENSE
bayketinymce_django-0.0.1.dist-info/METADATA
bayketinymce_django-0.0.1.dist-info/WHEEL
bayketinymce_django-0.0.1.dist-info/top_level.txt
bayketinymce_django-0.0.1.dist-info/RECORD
