Metadata-Version: 2.1
Name: bayketinymce-django
Version: 0.0.1
Summary: 一个简单的tinymce富文本编辑器的django第三方包！
Author-email: 轻编程 <1158920674@qq.com>
License: GNU GENERAL PUBLIC LICENSE
Project-URL: Homepage, http://www.bayke.shop
Project-URL: Bug Tracker, http://www.bayke.shop
Keywords: django,tinymce,baykeshop
Classifier: Programming Language :: Python :: 3
Classifier: License :: OSI Approved :: MIT License
Classifier: Operating System :: OS Independent
Requires-Python: >=3.8
License-File: LICENSE
